as4pgc/AS4PGC.py
as4pgc/__init__.py
as4pgc/progress_bar.py
as4pgc-1.1.5.dist-info/LICENSE
as4pgc-1.1.5.dist-info/METADATA
as4pgc-1.1.5.dist-info/WHEEL
as4pgc-1.1.5.dist-info/dependency_links.txt
as4pgc-1.1.5.dist-info/entry_points.txt
as4pgc-1.1.5.dist-info/top_level.txt
as4pgc-1.1.5.dist-info/RECORD
