Metadata-Version: 2.1
Name: as4pgc
Version: 1.1.5
Summary: Audio Steganography: compress, encrypt and hide a secret file inside an audio file (MP3, WAV, OGG, FLAC, ..)
Home-page: https://github.com/ClarkFieseln/as4pgc
Author: Clark Fieseln
Author-email: 
License: MIT
Keywords: steganography,stego,audio,hide,cryptography>=3.4.7,encryption,compression,security,cybersecurity,mp3,flac,ogg,wav,windows,linux
Platform: UNKNOWN
Classifier: License :: OSI Approved :: MIT License
Classifier: Programming Language :: Python :: 3.6
Classifier: Programming Language :: Python :: 3.7
Classifier: Programming Language :: Python :: 3.8
Classifier: Programming Language :: Python :: 3.9
Classifier: Development Status :: 4 - Beta
Classifier: Environment :: Console
Classifier: Intended Audience :: End Users/Desktop
Classifier: Intended Audience :: Developers
Classifier: Operating System :: Microsoft :: Windows :: Windows 10
Classifier: Operating System :: POSIX :: Linux
Classifier: Topic :: Security
Requires-Dist: SoundFile
Requires-Dist: bitarray
Requires-Dist: cryptography
Requires-Dist: dataclasses
Requires-Dist: matplotlib
Requires-Dist: numpy
Requires-Dist: scipy
Requires-Dist: simpleaudio
Requires-Dist: tinytag
